setup.py
markupsc/__main__.py
markupsc.egg-info/PKG-INFO
markupsc.egg-info/SOURCES.txt
markupsc.egg-info/dependency_links.txt
markupsc.egg-info/top_level.txt