Metadata-Version: 1.0
Name: markupsc
Version: 0.0.1
Summary: Server hosting made... easy!
Home-page: UNKNOWN
Author: UNKNOWN
Author-email: UNKNOWN
License: UNKNOWN
Platform: UNKNOWN
